setup.cfg
setup.py
layout/__init__.py
layout/rl_utils.py
layout.egg-info/PKG-INFO
layout.egg-info/SOURCES.txt
layout.egg-info/dependency_links.txt
layout.egg-info/not-zip-safe
layout.egg-info/top_level.txt
layout/datatypes/__init__.py
layout/datatypes/output.py
layout/datatypes/parse_dimensions.py
layout/datatypes/position.py
layout/elements/__init__.py
layout/elements/image.py
layout/elements/lines.py
layout/elements/mark.py
layout/elements/space.py
layout/elements/text.py
layout/managers/__init__.py
layout/managers/align.py
layout/managers/box.py
layout/managers/clip.py
layout/managers/directional.py
layout/managers/fixed.py
layout/managers/grid.py
layout/managers/jitter.py
layout/managers/margins.py
layout/managers/overlay.py
layout/managers/recursion.py
layout/managers/root.py
layout/managers/transform.py
layout/pages/__init__.py
layout/pages/imposition.py
layout/pages/output.py