Metadata-Version: 1.1
Name: layout
Version: 0.4.0
Summary: Content Layout Engine
Home-page: http://github.com/idmillington/layout
Author: Ian Millington
Author-email: idmillington@googlemail.com
License: UNKNOWN
Download-URL: https://github.com/idmillington/layout/tarball/master
Keywords: pdf,layout,print,design
Platform: UNKNOWN
Classifier: Programming Language :: Python
Classifier: Development Status :: 4 - Beta
Classifier: Environment :: Console
Classifier: Intended Audience :: Developers
Classifier: License :: OSI Approved :: MIT License
Classifier: Operating System :: OS Independent
Classifier: Topic :: Multimedia :: Graphics
